gblearn/__init__.py
gblearn/analysis.py
gblearn/base.py
gblearn/elements.py
gblearn/gb.py
gblearn/io.py
gblearn/lae.py
gblearn/lammps.py
gblearn/msg.py
gblearn/selection.py
gblearn/utility.py
gblearn/xyz.py
gblearn-0.4.1.dist-info/LICENSE.md
gblearn-0.4.1.dist-info/METADATA
gblearn-0.4.1.dist-info/WHEEL
gblearn-0.4.1.dist-info/top_level.txt
gblearn-0.4.1.dist-info/RECORD
