Metadata-Version: 2.1
Name: gblearn
Version: 0.4.1
Summary: Machine learning grain boundary properties and structure.
Home-page: https://github.com/rosenbrockc/gblearn
Author: Conrad W Rosenbrock, Derek M Hensley
Author-email: rosenbrockc@gmail.com, hensley.derek58@gmail.com
License: UNKNOWN
Platform: UNKNOWN
Classifier: Development Status :: 4 - Beta
Classifier: Intended Audience :: Science/Research
Classifier: Natural Language :: English
Classifier: Operating System :: MacOS
Classifier: Programming Language :: Python
Classifier: Programming Language :: Python :: 2
Classifier: Programming Language :: Python :: 2.7
Requires-Dist: argparse
Requires-Dist: termcolor
Requires-Dist: numpy
Requires-Dist: matplotlib
Requires-Dist: tqdm
Requires-Dist: ase
Requires-Dist: pycsoap
Requires-Dist: falconn (==1.3.0)
